dwellir_harvester/__init__.py
dwellir_harvester/collector_base.py
dwellir_harvester/core.py
dwellir_harvester/rpc_common.py
dwellir_harvester/rpc_evm.py
dwellir_harvester/rpc_substrate.py
dwellir_harvester/systemd_utils.py
dwellir_harvester/collectors/__init__.py
dwellir_harvester/collectors/dummychain.py
dwellir_harvester/collectors/file_ingest.py
dwellir_harvester/collectors/host.py
dwellir_harvester/collectors/juju.py
dwellir_harvester/collectors/null.py
dwellir_harvester/collectors/polkadot.py
dwellir_harvester/data/blockchain_node_metadata.schema.json
dwellir_harvester/lib/__init__.py
dwellir_harvester/lib/run.py
dwellir_harvester_lib-0.0.5.dist-info/METADATA
dwellir_harvester_lib-0.0.5.dist-info/WHEEL
dwellir_harvester_lib-0.0.5.dist-info/top_level.txt
dwellir_harvester_lib-0.0.5.dist-info/RECORD
