Metadata-Version: 2.4
Name: dwellir-harvester-lib
Version: 0.0.5
Summary: Core API for dwellir-harvester: collector bases, types, loaders, and helpers.
License: MIT
Classifier: Programming Language :: Python :: 3
Classifier: Programming Language :: Python :: 3.9
Classifier: Programming Language :: Python :: 3.10
Classifier: Programming Language :: Python :: 3.11
Classifier: Programming Language :: Python :: 3.12
Classifier: Operating System :: OS Independent
Classifier: Intended Audience :: Developers
Classifier: Topic :: Internet
Requires-Python: >=3.9
Requires-Dist: jsonschema>=4.10.3
Requires-Dist: requests>=2.31.0
Requires-Dist: psutil>=5.9.8
Requires-Dist: PyYAML>=6.0
